pahlavi/__init__.py
pahlavi/main.py
pahlavi-0.3.2.dist-info/METADATA
pahlavi-0.3.2.dist-info/WHEEL
pahlavi-0.3.2.dist-info/top_level.txt
pahlavi-0.3.2.dist-info/RECORD
