Metadata-Version: 2.4
Name: pahlavi
Version: 0.3.2
Summary: A compact toolkit for Iran's past: convert dates & compare currency and new features
Author-email: Behnam Alamshahi <b_alamshahi@outlook.com>
License: MIT
Keywords: jalali,pahlavi,calendar,currency
Classifier: Programming Language :: Python :: 3
Classifier: Programming Language :: Python :: 3.7
Classifier: Programming Language :: Python :: 3.8
Classifier: Programming Language :: Python :: 3.9
Classifier: Programming Language :: Python :: 3.10
Classifier: Programming Language :: Python :: 3.11
Classifier: License :: OSI Approved :: MIT License
Classifier: Operating System :: OS Independent
Classifier: Development Status :: 4 - Beta
Classifier: Intended Audience :: Developers
Classifier: Topic :: Software Development :: Libraries
Classifier: Topic :: Utilities
Requires-Python: >=3.7
Requires-Dist: jdatetime
Requires-Dist: requests
Requires-Dist: beautifulsoup4
